commonfilters/__init__.py
commonfilters/filter_coupling_policy.py
commonfilters/filters.py
commonfilters-0.0.4.dist-info/METADATA
commonfilters-0.0.4.dist-info/WHEEL
commonfilters-0.0.4.dist-info/licenses/LICENSE
commonfilters-0.0.4.dist-info/RECORD
